result_caching/__init__.py
result_caching-0.1.0.dist-info/METADATA
result_caching-0.1.0.dist-info/WHEEL
result_caching-0.1.0.dist-info/top_level.txt
result_caching-0.1.0.dist-info/RECORD
