Metadata-Version: 2.1
Name: result_caching
Version: 0.1.0
Summary: Cache results for re-use
Home-page: https://github.com/brain-score/result_caching
Author: Martin Schrimpf
Author-email: martin.schrimpf@outlook.com
License: MIT license
Keywords: caching
Classifier: Development Status :: 2 - Pre-Alpha
Classifier: Intended Audience :: Developers
Classifier: License :: OSI Approved :: MIT License
Classifier: Natural Language :: English
Classifier: Programming Language :: Python :: 3.11
Requires-Dist: numpy >=1.17
Requires-Dist: xarray
Requires-Dist: dask[array]
